MANIFEST.in
setup.py
bgionline/__init__.py
bgionline/api.py
bgionline/env.py
bgionline/exceptions.py
bgionline/version.py
bgionline.egg-info/PKG-INFO
bgionline.egg-info/SOURCES.txt
bgionline.egg-info/dependency_links.txt
bgionline.egg-info/entry_points.txt
bgionline.egg-info/not-zip-safe
bgionline.egg-info/requires.txt
bgionline.egg-info/top_level.txt
bgionline/bindings/__init__.py
bgionline/bindings/project.py
bgionline/cli/__init__.py
bgionline/packages/__init__.py
bgionline/scripts/__init__.py
bgionline/scripts/bo.py
bgionline/tests/__init__.py
bgionline/tests/test_utils.py
bgionline/utils/__init__.py
bgionline/utils/config.py
bgionline/utils/download_file.py
bgionline/utils/prettytable.py
bgionline/utils/print_funtion.py
bgionline/utils/sh_util.py
bgionline/utils/upload_file.py