Metadata-Version: 1.0
Name: bgionline
Version: 3.0.3
Summary: BGI Online Platform API bindings for Python
Home-page: https://www.bgionline.cn
Author: bgionline
Author-email: bgionline@genomics.cn
License: Apache Software License
Platform: UNKNOWN
